[{"timestamp":1712527444908,"files":[{"filename":"bundle.dddf4.css","previous":617,"size":617,"diff":0},{"filename":"bundle.*****.esm.js","previous":8963,"size":8969,"diff":6},{"filename":"polyfills.*****.esm.js","previous":2317,"size":2328,"diff":11},{"filename":"route-home.chunk.df06b.css","previous":407,"size":407,"diff":0},{"filename":"route-home.chunk.*****.esm.js","previous":606,"size":606,"diff":0},{"filename":"route-profile.chunk.*****.esm.js","previous":1421,"size":1421,"diff":0},{"filename":"sw-esm.js","previous":11423,"size":11447,"diff":24},{"filename":"sw.js","previous":11418,"size":11443,"diff":25},{"filename":"bundle.0e31e.js","previous":9007,"size":0,"diff":-9007},{"filename":"polyfills.2e20e.js","previous":2414,"size":0,"diff":-2414},{"filename":"route-home.chunk.7ff6c.js","previous":607,"size":607,"diff":0},{"filename":"route-profile.chunk.1b7e9.js","previous":1945,"size":1945,"diff":0},{"filename":"index.html","previous":1698,"size":1705,"diff":7},{"filename":"200.html","previous":671,"size":679,"diff":8},{"filename":"bundle.3069f.js","previous":0,"size":9017,"diff":9017},{"filename":"polyfills.21303.js","previous":0,"size":2427,"diff":2427}]},{"timestamp":1712527196551,"files":[{"filename":"ssr-build/ssr-bundle.47f9a.css","previous":930,"size":0,"diff":-930},{"filename":"ssr-build/ssr-bundle.js","previous":8749,"size":0,"diff":-8749},{"filename":"bundle.dddf4.css","previous":0,"size":617,"diff":617},{"filename":"bundle.*****.esm.js","previous":0,"size":8963,"diff":8963},{"filename":"polyfills.*****.esm.js","previous":0,"size":2317,"diff":2317},{"filename":"route-home.chunk.df06b.css","previous":0,"size":407,"diff":407},{"filename":"route-home.chunk.*****.esm.js","previous":0,"size":606,"diff":606},{"filename":"route-profile.chunk.*****.esm.js","previous":0,"size":1421,"diff":1421},{"filename":"sw-esm.js","previous":0,"size":11423,"diff":11423},{"filename":"sw.js","previous":0,"size":11418,"diff":11418},{"filename":"bundle.0e31e.js","previous":0,"size":9007,"diff":9007},{"filename":"polyfills.2e20e.js","previous":0,"size":2414,"diff":2414},{"filename":"route-home.chunk.7ff6c.js","previous":0,"size":607,"diff":607},{"filename":"route-profile.chunk.1b7e9.js","previous":0,"size":1945,"diff":1945},{"filename":"index.html","previous":0,"size":1698,"diff":1698},{"filename":"200.html","previous":0,"size":671,"diff":671}]}]
